[
  {
    "_id": "survey-data-entry",
    "title": "Survey Data Entry Specialist",
    "department": "Data Operations",
    "salary": "$15 - $20/hour ($2,600 - $3,466/month)",
    "location": "Remote",
    "jobType": "Full Time",
    "workHours": "9:00 AM - 5:00 PM EST (Flexible +/- 2 hours)",
    "experience": "Entry Level",
    "skills": [
      "Typing speed 45+ WPM",
      "Basic Excel/Google Sheets",
      "Attention to detail (95%+ accuracy)",
      "Time management"
    ],
    "requirements": [
      "Must be legally authorized to work in the U.S. (citizen, green card, EAD)",
      "Origin from Bangladesh and Pakistan are not allowed",
      "Must pass Veriff identity verification",
      "High school diploma minimum",
      "Quiet home workspace with reliable internet (minimum 25 Mbps)"
    ],
    "responsibilities": [
      "Accurately transcribe 200+ survey responses daily",
      "Validate data against quality control standards",
      "Flag inconsistent or suspicious responses",
      "Maintain 98%+ accuracy rate",
      "Participate in weekly calibration sessions"
    ],
    "benefits": [
      "Health insurance after 90 days",
      "401(k) with 3% company match",
      "$500/year professional development stipend",
      "Quarterly performance bonuses"
    ],
    "hiring": 5,
    "applicationDeadline": "2025-09-15",
    "startDate": "2024-01-08",
    "shortDescription": "Remote data entry position processing survey responses with quality control responsibilities.",
    "description": "Join our Data Operations team as we process over 50,000 monthly survey responses from market research studies. You'll be trained on our proprietary data entry platform and quality assurance protocols. After the initial 2-week training period, you'll be expected to maintain 200+ daily entries with 98% accuracy. The role includes weekly team meetings and monthly one-on-ones with your supervisor. We provide all necessary software - you just need a Windows/Mac computer with dual monitor capability (we provide a stipend for second monitor purchase)."
  },
  {
    "_id": "survey-support-agent",
    "title": "Survey Support Specialist",
    "department": "Client Services",
    "salary": "$17 - $22/hour ($2,946 - $3,813/month)",
    "location": "Remote",
    "jobType": "Full Time",
    "workHours": "Shifts between 8:00 AM - 8:00 PM EST (Rotating weekends)",
    "experience": "Entry Level",
    "skills": [
      "Customer service orientation",
      "Technical troubleshooting",
      "Conflict resolution",
      "Multitasking in fast-paced environment"
    ],
    "requirements": [
      "Native or bilingual English proficiency",
      "Origin from Bangladesh and Pakistan are not allowed",
      "Must pass Veriff identity verification",
      "1+ year in customer-facing role preferred",
      "Dedicated workspace with headset"
    ],
    "responsibilities": [
      "Handle 50+ live chats/emails daily",
      "Maintain 90%+ customer satisfaction score",
      "Document all interactions in Zendesk",
      "Escalate technical issues to Tier 2 support",
      "Participate in monthly product training"
    ],
    "benefits": [
      "Health, dental, and vision insurance",
      "15 days PTO + holidays",
      "$1,000/year education reimbursement",
      "Monthly team building activities"
    ],
    "hiring": 8,
    "applicationDeadline": "2025-09-15",
    "startDate": "2024-01-16",
    "shortDescription": "Provide frontline support for survey participants via email and live chat.",
    "description": "As the first point of contact for our survey platform users, you'll resolve technical issues, answer eligibility questions, and ensure positive participant experiences. After completing our 3-week paid training program (including product knowledge and de-escalation techniques), you'll join a team of 15 support professionals handling 10,000+ monthly inquiries. Metrics include response time (under 2 minutes for chat), resolution rate (85% first contact), and customer satisfaction scores. Growth paths include Quality Assurance coaching or Team Lead positions."
  },
  {
    "_id": "us-based-field-agent",
    "title": "Field Research Coordinator",
    "department": "Field Operations",
    "salary": "$18 - $24/hour ($3,120 - $4,160/month) + mileage reimbursement",
    "location": "Austin, TX",
    "jobType": "Full Time",
    "workHours": "Variable hours including evenings/weekends",
    "experience": "Entry Level",
    "skills": [
      "Public speaking",
      "Persuasive communication",
      "Basic tablet/smartphone proficiency",
      "Cultural sensitivity"
    ],
    "requirements": [
      "Must reside within 30 miles of posted location",
      "Valid driver's license and clean record",
      "Ability to lift 25 lbs (materials)",
      "Background check required",
      "Origin from Bangladesh and Pakistan are not allowed"
    ],
    "responsibilities": [
      "Approach 100+ participants weekly at designated locations",
      "Administer 10-15 minute structured interviews",
      "Accurately record responses in SurveyCTO app",
      "Manage incentive distribution",
      "Submit daily activity reports"
    ],
    "benefits": [
      "Health benefits starting day 1",
      "Paid travel time between sites",
      "$50/month phone stipend",
      "Performance bonuses quarterly"
    ],
    "hiring": 6,
    "applicationDeadline": "2025-09-15",
    "startDate": "2024-01-02",
    "shortDescription": "Conduct in-person surveys at retail locations and public venues.",
    "description": "Our field team collects crucial consumer insights at shopping malls, grocery stores, and public events. You'll complete a 1-week paid training covering research ethics, approach techniques, and data collection protocols. Daily expectations include visiting 3-4 pre-assigned locations, obtaining 15-20 completed surveys per location, and securely transmitting data. We provide all equipment including tablet, branded vest, and collateral materials. This position involves significant walking/standing and interaction with diverse populations. Advancement opportunities include Field Supervisor or Project Coordinator roles."
  },
  {
    "_id": "junior-web-developer",
    "title": "Associate Front-End Developer",
    "department": "Engineering",
    "salary": "$25 - $32/hour ($4,333 - $5,546/month)",
    "location": "Remote",
    "jobType": "Full Time",
    "workHours": "Flexible within core hours 10:00 AM - 3:00 PM EST",
    "experience": "1-2 years",
    "skills": [
      "HTML5/CSS3",
      "JavaScript (ES6+)",
      "React fundamentals",
      "Git version control",
      "Responsive design principles"
    ],
    "requirements": [
      "Bootcamp certification or CS degree",
      "Portfolio demonstrating basic projects",
      "Origin from Bangladesh and Pakistan are not allowed",
      "Must pass technical assessment",
      "Veriff identity verification"
    ],
    "responsibilities": [
      "Implement UI components from Figma designs",
      "Fix priority 3-4 bugs weekly",
      "Write unit tests for new components",
      "Participate in code reviews",
      "Document technical processes"
    ],
    "benefits": [
      "Comprehensive tech stack training",
      "$2,000/year conference budget",
      "Home office setup stipend",
      "Stock options after 1 year"
    ],
    "hiring": 3,
    "applicationDeadline": "2025-09-15",
    "startDate": "2024-02-01",
    "shortDescription": "Entry-level developer position maintaining survey platform front-end.",
    "description": "Join our 12-person engineering team maintaining a platform serving 500,000+ monthly users. You'll work primarily in our React/TypeScript codebase under the guidance of senior developers. The first 3 months include structured onboarding with weekly pairing sessions and progressively complex tickets. Expect to spend 60% on feature development, 30% bug fixes, and 10% professional development. We follow Agile methodology with 2-week sprints and biweekly retrospectives. Performance reviews at 3, 6, and 12 months determine promotion to Mid-Level Developer."
  },
  {
    "_id": "research-assistant",
    "title": "Market Research Assistant",
    "department": "Research & Analytics",
    "salary": "$16 - $21/hour ($2,773 - $3,640/month)",
    "location": "Remote",
    "jobType": "Full Time",
    "workHours": "Monday-Friday, 10:00 AM - 6:00 PM EST",
    "experience": "Entry Level",
    "skills": [
      "Basic data analysis",
      "Google Sheets/Excel",
      "Report writing",
      "Attention to detail"
    ],
    "requirements": [
      "Bachelor's degree in Social Sciences, Business, or related field",
      "Must be authorized to work in the U.S.",
      "Origin from Bangladesh and Pakistan are not allowed",
      "Veriff identity verification required",
      "Comfort with basic statistics"
    ],
    "responsibilities": [
      "Clean and organize survey datasets",
      "Create basic data visualizations",
      "Assist with report preparation",
      "Conduct quality checks on research instruments",
      "Support senior researchers with ad-hoc tasks"
    ],
    "benefits": [
      "Health insurance with 80% premium coverage",
      "401(k) matching up to 4%",
      "$750 annual training budget",
      "Flexible work arrangements"
    ],
    "hiring": 4,
    "applicationDeadline": "2025-09-15",
    "startDate": "2024-02-05",
    "shortDescription": "Support our research team with data preparation and basic analysis tasks.",
    "description": "Join our growing research team as we deliver insights to Fortune 500 clients. You'll work closely with project managers to prepare client-ready deliverables, ensuring data accuracy and visual clarity. The first month includes intensive training on our research methodologies and reporting standards. This role serves as a gateway to more advanced analyst positions - 60% of our Research Assistants are promoted within 18 months. Ideal for recent graduates looking to launch their market research careers."
  },
  {
    "_id": "it-support",
    "title": "IT Help Desk Technician",
    "department": "Information Technology",
    "salary": "$20 - $25/hour ($3,467 - $4,333/month)",
    "location": "Austin, TX",
    "jobType": "Full Time",
    "workHours": "Rotating shifts covering 7:00 AM - 7:00 PM local time",
    "experience": "Entry Level",
    "skills": [
      "Troubleshooting",
      "Active Directory",
      "Ticket management",
      "Customer service"
    ],
    "requirements": [
      "CompTIA A+ certification (or willingness to obtain within 3 months)",
      "Associate's degree in IT or related field",
      "Must pass comprehensive background check",
      "Origin from Bangladesh and Pakistan are not allowed",
      "On-site availability required"
    ],
    "responsibilities": [
      "Resolve 15+ tickets daily",
      "Provide Level 1 technical support",
      "Configure new hire equipment",
      "Document solutions in knowledge base",
      "Escalate complex issues to sysadmins"
    ],
    "benefits": [
      "Certification reimbursement",
      "On-call differential pay",
      "Tech equipment allowance",
      "Clear path to sysadmin roles"
    ],
    "hiring": 3,
    "applicationDeadline": "2025-09-15",
    "startDate": "2024-01-29",
    "shortDescription": "Frontline technical support for our corporate offices.",
    "description": "As the face of our IT department, you'll provide white-glove service to 150+ employees across our three office locations. This role combines technical problem-solving with exceptional customer service - you'll handle everything from password resets to hardware configurations. Our structured 90-day onboarding includes shadowing senior technicians and progressive responsibility increases. The IT team operates on a follow-the-sun model with opportunities to transition to night shift or sysadmin roles after 12 months. Must be comfortable working in-office with occasional after-hours support rotations."
  },
  {
    "_id": "junior-web-designer",
    "title": "Junior Web Designer",
    "department": "Creative",
    "salary": "$22 - $28/hour ($3,813 - $4,853/month)",
    "location": "Remote or Austin, TX",
    "jobType": "Full Time",
    "workHours": "Flexible within core hours 10:00 AM - 3:00 PM CST",
    "experience": "0-2 years",
    "skills": [
      "Figma/Sketch",
      "Basic HTML/CSS",
      "UI/UX principles",
      "Adobe Creative Suite",
      "Responsive design"
    ],
    "requirements": [
      "Design portfolio demonstrating layout skills",
      "Associate's degree or bootcamp certificate",
      "Hybrid/remote options available",
      "Veriff verification for remote workers",
      "Origin from Bangladesh and Pakistan are not allowed"
    ],
    "responsibilities": [
      "Create 3-5 landing page mockups weekly",
      "Design survey interface components",
      "Maintain design system documentation",
      "Collaborate with frontend developers",
      "Conduct basic usability testing"
    ],
    "benefits": [
      "Creative software provided",
      "$1,500 annual hardware upgrade",
      "Mentorship program",
      "Flexible work arrangements",
      "Quarterly design workshop"
    ],
    "hiring": 2,
    "applicationDeadline": "2025-09-15",
    "startDate": "2024-03-04",
    "shortDescription": "Entry-level design role with flexible location options.",
    "description": "Work alongside our Creative Director and marketing team to produce visually compelling digital experiences. This role offers both remote and in-office (Austin) options - remote team members receive monthly co-working stipends. You'll start with smaller design tasks (buttons, form fields, icons) before progressing to complete page layouts. Our 6-month ramp-up program includes weekly design critiques and UX fundamentals training. Ideal for recent graduates or career changers building their digital design portfolio. Tools provided include Figma Organization, Adobe Creative Cloud, and access to our design system library."
  }
]